swift/Swift.py
swift/SwiftElement.py
swift/SwiftRoute.py
swift/__init__.py
swift/phys.cp312-win_amd64.pyd
swift/rtc.py
swift/core/linalg.h
swift/core/phys.cpp
swift/core/phys.h
swift/core/Eigen/Cholesky
swift/core/Eigen/CholmodSupport
swift/core/Eigen/Core
swift/core/Eigen/Dense
swift/core/Eigen/Eigen
swift/core/Eigen/Eigenvalues
swift/core/Eigen/Geometry
swift/core/Eigen/Householder
swift/core/Eigen/IterativeLinearSolvers
swift/core/Eigen/Jacobi
swift/core/Eigen/KLUSupport
swift/core/Eigen/LU
swift/core/Eigen/MetisSupport
swift/core/Eigen/OrderingMethods
swift/core/Eigen/PaStiXSupport
swift/core/Eigen/PardisoSupport
swift/core/Eigen/QR
swift/core/Eigen/QtAlignedMalloc
swift/core/Eigen/SPQRSupport
swift/core/Eigen/SVD
swift/core/Eigen/Sparse
swift/core/Eigen/SparseCholesky
swift/core/Eigen/SparseCore
swift/core/Eigen/SparseLU
swift/core/Eigen/SparseQR
swift/core/Eigen/StdDeque
swift/core/Eigen/StdList
swift/core/Eigen/StdVector
swift/core/Eigen/SuperLUSupport
swift/core/Eigen/UmfPackSupport
swift/core/Eigen/src/Cholesky/LDLT.h
swift/core/Eigen/src/Cholesky/LLT.h
swift/core/Eigen/src/Cholesky/LLT_LAPACKE.h
swift/core/Eigen/src/CholmodSupport/CholmodSupport.h
swift/core/Eigen/src/Core/ArithmeticSequence.h
swift/core/Eigen/src/Core/Array.h
swift/core/Eigen/src/Core/ArrayBase.h
swift/core/Eigen/src/Core/ArrayWrapper.h
swift/core/Eigen/src/Core/Assign.h
swift/core/Eigen/src/Core/AssignEvaluator.h
swift/core/Eigen/src/Core/Assign_MKL.h
swift/core/Eigen/src/Core/BandMatrix.h
swift/core/Eigen/src/Core/Block.h
swift/core/Eigen/src/Core/BooleanRedux.h
swift/core/Eigen/src/Core/CommaInitializer.h
swift/core/Eigen/src/Core/ConditionEstimator.h
swift/core/Eigen/src/Core/CoreEvaluators.h
swift/core/Eigen/src/Core/CoreIterators.h
swift/core/Eigen/src/Core/CwiseBinaryOp.h
swift/core/Eigen/src/Core/CwiseNullaryOp.h
swift/core/Eigen/src/Core/CwiseTernaryOp.h
swift/core/Eigen/src/Core/CwiseUnaryOp.h
swift/core/Eigen/src/Core/CwiseUnaryView.h
swift/core/Eigen/src/Core/DenseBase.h
neura_swift-0.0.2.dist-info/LICENSE
neura_swift-0.0.2.dist-info/METADATA
neura_swift-0.0.2.dist-info/WHEEL
neura_swift-0.0.2.dist-info/top_level.txt
neura_swift-0.0.2.dist-info/RECORD
