Metadata-Version: 2.1
Name: neura-swift
Version: 0.0.2
Summary: A Python/Javascript Robot Simulator and Visualiser
Author-email: Jesse Haviland <j.haviland@qut.edu.au>, Peter Corke <rvc@petercorke.com>, Jens Temminghoff <jens.temminghoff@neura-robotics.com>
License: MIT License
Project-URL: homepage, https://github.com/JTem/neura_swift
Project-URL: repository, https://github.com/JTem/neura_swift
Keywords: python,robotics,robotics-toolbox,kinematics,dynamics,motion-planning,trajectory-generation,jacobian,hessian,control,simulation,robot-manipulator,mobile-robot
Classifier: Development Status :: 5 - Production/Stable
Classifier: Intended Audience :: Developers
Classifier: License :: OSI Approved :: MIT License
Classifier: Programming Language :: Python :: 3.7
Classifier: Programming Language :: Python :: 3.8
Classifier: Programming Language :: Python :: 3.9
Classifier: Programming Language :: Python :: 3.10
Classifier: Programming Language :: Python :: 3.11
Requires-Python: >=3.7
License-File: LICENSE
Requires-Dist: numpy >=1.17.4
Requires-Dist: spatialgeometry >=1.0.0
Requires-Dist: websockets
Provides-Extra: dev
Requires-Dist: black ; extra == 'dev'
Requires-Dist: neura-roboticstoolbox >=0.0.2 ; extra == 'dev'
Requires-Dist: neura-swift ; extra == 'dev'
Requires-Dist: pytest ; extra == 'dev'
Requires-Dist: pytest-cov ; extra == 'dev'
Requires-Dist: flake8 ; extra == 'dev'
Requires-Dist: pyyaml ; extra == 'dev'
Provides-Extra: docs
Requires-Dist: sphinx ; extra == 'docs'
Requires-Dist: sphinx-rtd-theme ; extra == 'docs'
Requires-Dist: sphinx-autorun ; extra == 'docs'
Provides-Extra: nb
Requires-Dist: ipython ; extra == 'nb'
Requires-Dist: notebook ; extra == 'nb'
Provides-Extra: vision
Requires-Dist: aiortc ; extra == 'vision'
Requires-Dist: opencv-python ; extra == 'vision'
